agi_med_grpc_interceptors/__init__.py
agi_med_grpc_interceptors/base_interceptor.py
agi_med_grpc_interceptors/exc_handler_interceptor.py
agi_med_grpc_interceptors/logging_interceptor.py
agi_med_grpc_interceptors/exc/__init__.py
agi_med_grpc_interceptors/exc/base_grpc_error.py
agi_med_grpc_interceptors/models/__init__.py
agi_med_grpc_interceptors/models/default_value.py
agi_med_grpc_interceptors/models/error_details.py
agi_med_grpc_interceptors-3.2.0.dist-info/METADATA
agi_med_grpc_interceptors-3.2.0.dist-info/WHEEL
agi_med_grpc_interceptors-3.2.0.dist-info/top_level.txt
agi_med_grpc_interceptors-3.2.0.dist-info/RECORD
