Metadata-Version: 2.2
Name: agi_med_grpc_interceptors
Version: 3.2.0
Summary: Interceptors for grpc
Author: AGI-MED-TEAM
Requires-Python: >=3.11
Requires-Dist: grpcio~=1.68.1
Requires-Dist: grpcio-tools~=1.68.1
Requires-Dist: loguru~=0.7.2
Requires-Dist: pydantic~=2.9.2
